reading_parquet_file/__init__.py
reading_parquet_file/read_parquet.py
reading_parquet_file-0.0.3.dist-info/LICENSE
reading_parquet_file-0.0.3.dist-info/METADATA
reading_parquet_file-0.0.3.dist-info/WHEEL
reading_parquet_file-0.0.3.dist-info/top_level.txt
reading_parquet_file-0.0.3.dist-info/RECORD
