Metadata-Version: 2.1
Name: reading-parquet-file
Version: 0.0.3
Summary: To read the parquet file from azure blob storage
Author: RR
Author-email: rr@gmail.com
Classifier: Programming Language :: Python :: 3
Classifier: License :: OSI Approved :: MIT License
Classifier: Operating System :: OS Independent
Requires-Python: >=3.7
License-File: LICENSE
Requires-Dist: pandas
Requires-Dist: pyarrow
Requires-Dist: pyarrowfs-adlgen2
